xarray_simpleunits/__init__.py
xarray_simpleunits/units.py
xarray_simpleunits-0.0.5.dist-info/LICENSE
xarray_simpleunits-0.0.5.dist-info/METADATA
xarray_simpleunits-0.0.5.dist-info/WHEEL
xarray_simpleunits-0.0.5.dist-info/top_level.txt
xarray_simpleunits-0.0.5.dist-info/RECORD
