Metadata-Version: 2.2
Name: xarray_simpleunits
Version: 0.0.5
Summary: Simple unitful calculations with `xarray`
Home-page: https://github.com/st-bender/xarray-simpleunits
Author: Stefan Bender
Author-email: sbender@iaa.es
License: GPLv2
Classifier: Development Status :: 3 - Alpha
Classifier: Intended Audience :: Science/Research
Classifier: License :: OSI Approved :: GNU General Public License v2 (GPLv2)
Classifier: Programming Language :: Python
Classifier: Programming Language :: Python :: 2
Classifier: Programming Language :: Python :: 3
Classifier: Topic :: Scientific/Engineering :: Physics
Classifier: Topic :: Utilities
License-File: LICENSE
Requires-Dist: astropy
Requires-Dist: xarray
Provides-Extra: tests
Requires-Dist: pytest; extra == "tests"
Provides-Extra: all
Requires-Dist: pytest; extra == "all"
Dynamic: author
Dynamic: author-email
Dynamic: classifier
Dynamic: description
Dynamic: description-content-type
Dynamic: home-page
Dynamic: license
Dynamic: provides-extra
Dynamic: requires-dist
Dynamic: summary
